distributed_rate_limiter/__init__.py
distributed_rate_limiter/exceptions.py
distributed_rate_limiter/limiter.py
distributed_rate_limiter/types.py
distributed_rate_limiter/algorithms/__init__.py
distributed_rate_limiter/algorithms/base.py
distributed_rate_limiter/algorithms/token_bucket.py
distributed_rate_limiter/backends/__init__.py
distributed_rate_limiter/backends/base.py
distributed_rate_limiter/backends/redis_async.py
distributed_rate_limiter/backends/redis_sync.py
distributed_rate_limiter/middleware/__init__.py
distributed_rate_limiter/middleware/fastapi.py
distributed_rate_limiter/middleware/flask.py
distributed_rate_limiter/tests/__init__.py
distributed_rate_limiter/tests/conftest.py
distributed_rate_limiter/tests/test_fail_strategy.py
distributed_rate_limiter/tests/test_identity_validation.py
distributed_rate_limiter/tests/test_limiter_async.py
distributed_rate_limiter/tests/test_limiter_sync.py
distributed_rate_limiter-0.1.1.dist-info/METADATA
distributed_rate_limiter-0.1.1.dist-info/WHEEL
distributed_rate_limiter-0.1.1.dist-info/top_level.txt
distributed_rate_limiter-0.1.1.dist-info/RECORD
