Metadata-Version: 2.1
Name: distributed-rate-limiter
Version: 0.1.1
Summary: Redis-backed, horizontally scalable rate limiting for distributed systems
Author: Ayush Dubey
Requires-Python: >=3.8
Requires-Dist: redis >=4.5
